LICENSE
MANIFEST.in
README.rst
setup.cfg
setup.py
django_flat_theme.egg-info/PKG-INFO
django_flat_theme.egg-info/SOURCES.txt
django_flat_theme.egg-info/dependency_links.txt
django_flat_theme.egg-info/top_level.txt
flat/__init__.py
flat/static/admin/css/base.css
flat/static/admin/css/changelists.css
flat/static/admin/css/fonts.css
flat/static/admin/css/forms.css
flat/static/admin/css/login.css
flat/static/admin/css/rtl.css
flat/static/admin/css/widgets.css
flat/static/admin/fonts/LICENSE.txt
flat/static/admin/fonts/README.txt
flat/static/admin/fonts/Roboto-Bold-webfont.woff
flat/static/admin/fonts/Roboto-Light-webfont.woff
flat/static/admin/fonts/Roboto-Regular-webfont.woff
flat/static/admin/img/changelist-bg.gif
flat/static/admin/img/changelist-bg_rtl.gif
flat/static/admin/img/default-bg-reverse.gif
flat/static/admin/img/default-bg.gif
flat/static/admin/img/deleted-overlay.gif
flat/static/admin/img/icon-no.gif
flat/static/admin/img/icon-unknown.gif
flat/static/admin/img/icon-yes.gif
flat/static/admin/img/icon_addlink.gif
flat/static/admin/img/icon_alert.gif
flat/static/admin/img/icon_calendar.gif
flat/static/admin/img/icon_changelink.gif
flat/static/admin/img/icon_clock.gif
flat/static/admin/img/icon_deletelink.gif
flat/static/admin/img/icon_error.gif
flat/static/admin/img/icon_searchbox.png
flat/static/admin/img/icon_success.gif
flat/static/admin/img/inline-delete-8bit.png
flat/static/admin/img/inline-delete.png
flat/static/admin/img/inline-restore-8bit.png
flat/static/admin/img/inline-restore.png
flat/static/admin/img/inline-splitter-bg.gif
flat/static/admin/img/nav-bg-grabber.gif
flat/static/admin/img/nav-bg-reverse.gif
flat/static/admin/img/nav-bg-selected.gif
flat/static/admin/img/nav-bg.gif
flat/static/admin/img/selector-icons.gif
flat/static/admin/img/selector-search.gif
flat/static/admin/img/sorting-icons.gif
flat/static/admin/img/tooltag-add.png
flat/static/admin/img/tooltag-arrowright.png
flat/static/admin/img/gis/move_vertex_off.png
flat/static/admin/img/gis/move_vertex_off.svg
flat/static/admin/img/gis/move_vertex_on.png
flat/static/admin/img/gis/move_vertex_on.svg
flat/static/admin/img/svg/LICENSE
