Metadata-Version: 1.1
Name: django-flat-theme
Version: 1.1.1
Summary: A flat theme for Django admin interface. Modern, fresh, simple.
Home-page: https://github.com/elky/django-flat-theme
Author: Alex D
Author-email: mail@elky.me
License: BSD
Download-URL: https://github.com/elky/django-flat-theme/tarball/1.1.1
Keywords: django,admin,theme,interface
Platform: UNKNOWN
